shipyard/__init__.py
shipyard/__main__.py
shipyard/ansible/README.md
shipyard/api/__init__.py
shipyard/api/__main__.py
shipyard/api/app.py
shipyard/api/main.py
shipyard/api/v1/__init__.py
shipyard/api/v1/app.py
shipyard/cli/__init__.py
shipyard/cli/__main__.py
shipyard/cli/main.py
shipyard/colony/__init__.py
shipyard/colony/notes.py
shipyard/db.py
shipyard/deploy/__init__.py
shipyard/envoy/__init__.py
shipyard/envoy/tasks.py
shipyard/envoy/tunnel.py
shipyard/models.py
shipyard/settings.py
shipyard/tasks.py
shipyard/tsk/__init__.py
shipyard/tsk/__main__.py
shipyard/tsk/app.py
shipyard/tsk/main.py
shipyard/vigil/__init__.py
shipyard_urbit-0.1.4.dist-info/LICENSE.Apache-2.0
shipyard_urbit-0.1.4.dist-info/LICENSE.LGPL-2.1-or-later
shipyard_urbit-0.1.4.dist-info/METADATA
shipyard_urbit-0.1.4.dist-info/WHEEL
shipyard_urbit-0.1.4.dist-info/entry_points.txt
shipyard_urbit-0.1.4.dist-info/RECORD
