Metadata-Version: 2.1
Name: shipyard-urbit
Version: 0.1.4
Summary: Urbit hosting and automation platform
License: Apache-2.0
Author: nodreb-borrus
Author-email: nodreb@borr.us
Requires-Python: >=3.8,<4.0
Classifier: License :: OSI Approved :: Apache Software License
Classifier: Programming Language :: Python :: 3
Classifier: Programming Language :: Python :: 3.8
Classifier: Programming Language :: Python :: 3.9
Classifier: Programming Language :: Python :: 3.10
Classifier: Programming Language :: Python :: 3.11
Requires-Dist: aiohttp (>=3.8.5,<4.0.0)
Requires-Dist: aioprocessing (>=2.0.1,<3.0.0)
Requires-Dist: ansible-runner (>=2.3.4,<3.0.0)
Requires-Dist: docker[ssh] (>=6.1.3,<7.0.0)
Requires-Dist: fastapi (>=0.103.2,<0.104.0)
Requires-Dist: gunicorn (>=21.2.0,<22.0.0)
Requires-Dist: psycopg2-binary (>=2.9.3,<3.0.0)
Requires-Dist: python-dotenv (>=1.0.0,<2.0.0)
Requires-Dist: sqlmodel (>=0.0.8,<0.0.9)
Requires-Dist: typer[all] (>=0.9.0,<0.10.0)
Requires-Dist: uvicorn[standard] (>=0.23.2,<0.24.0)
